scorpionsql/__init__.py
scorpionsql/aggerror.py
scorpionsql/db.py
scorpionsql/errfunc.py
scorpionsql/functions.py
scorpionsql/settings.py
scorpionsql/sql.py
scorpionsql/sqlparser.py
scorpionsql-0.0.6.dist-info/LICENSE
scorpionsql-0.0.6.dist-info/METADATA
scorpionsql-0.0.6.dist-info/WHEEL
scorpionsql-0.0.6.dist-info/top_level.txt
scorpionsql-0.0.6.dist-info/RECORD
