Metadata-Version: 2.1
Name: scorpionsql
Version: 0.0.6
Summary: SQL-related and other shared packages used by scorpion and dbwipes
Home-page: http://github.com/sirrice/scorpionsql
Author: Eugene Wu
Author-email: eugenewu@mit.edu
License: MIT
License-File: LICENSE
Requires-Dist: psycopg2-binary
Requires-Dist: sqlalchemy
Requires-Dist: numpy
Requires-Dist: pyparsing
